naspi/__init__.py
naspi/naspi.py
naspi-0.1.9.3.dist-info/LICENSE
naspi-0.1.9.3.dist-info/METADATA
naspi-0.1.9.3.dist-info/WHEEL
naspi-0.1.9.3.dist-info/entry_points.txt
naspi-0.1.9.3.dist-info/top_level.txt
naspi-0.1.9.3.dist-info/RECORD
