Metadata-Version: 2.1
Name: naspi
Version: 0.1.9.3
Summary: Simple NAS for Raspberry Pi
Home-page: https://github.com/fgiroult321/simple-nas-pi
Author: Frederic Giroult
Author-email: frederic.giroult@gmail.com
License: MIT
Platform: UNKNOWN
Classifier: Programming Language :: Python :: 3
Classifier: License :: OSI Approved :: MIT License
Classifier: Operating System :: POSIX :: Linux
Requires-Python: >=3.6
Requires-Dist: boto3
Requires-Dist: awscli
